odoo/addons/mrp_account_bom_attribute_match/README.rst
odoo/addons/mrp_account_bom_attribute_match/__init__.py
odoo/addons/mrp_account_bom_attribute_match/__manifest__.py
odoo/addons/mrp_account_bom_attribute_match/i18n/es.po
odoo/addons/mrp_account_bom_attribute_match/i18n/it.po
odoo/addons/mrp_account_bom_attribute_match/i18n/mrp_account_bom_attribute_match.pot
odoo/addons/mrp_account_bom_attribute_match/models/__init__.py
odoo/addons/mrp_account_bom_attribute_match/models/product_product.py
odoo/addons/mrp_account_bom_attribute_match/readme/CONTRIBUTORS.rst
odoo/addons/mrp_account_bom_attribute_match/readme/DESCRIPTION.rst
odoo/addons/mrp_account_bom_attribute_match/static/description/icon.png
odoo/addons/mrp_account_bom_attribute_match/static/description/index.html
odoo/addons/mrp_account_bom_attribute_match/tests/__init__.py
odoo/addons/mrp_account_bom_attribute_match/tests/test_mrp_account_bom_attribute_match.py
odoo_addon_mrp_account_bom_attribute_match-15.0.1.1.1.5.dist-info/METADATA
odoo_addon_mrp_account_bom_attribute_match-15.0.1.1.1.5.dist-info/WHEEL
odoo_addon_mrp_account_bom_attribute_match-15.0.1.1.1.5.dist-info/top_level.txt
odoo_addon_mrp_account_bom_attribute_match-15.0.1.1.1.5.dist-info/RECORD
